twcli/__init__.py
twcli/app.py
twcli/utils.py
twcli/future/__init__.py
twcli/future/commands.py
twcli/option/__init__.py
twcli/option/commands.py
twcli/option/option.py
twcli/pairs/__init__.py
twcli/pairs/commands.py
twcli/pairs/sizing.py
twcli/plot/__init__.py
twcli/plot/commands.py
twcli/plot/plot.py
twcli/quant/__init__.py
twcli/quant/models.py
tastyworks_cli-1.0.3.dist-info/LICENSE
tastyworks_cli-1.0.3.dist-info/METADATA
tastyworks_cli-1.0.3.dist-info/WHEEL
tastyworks_cli-1.0.3.dist-info/entry_points.txt
tastyworks_cli-1.0.3.dist-info/top_level.txt
tastyworks_cli-1.0.3.dist-info/RECORD
