Metadata-Version: 2.1
Name: tastyworks-cli
Version: 1.0.3
Summary: An easy-to-use command line interface for Tastyworks!
Home-page: https://github.com/Graeme22/tastyworks-cli/
Author: Graeme Holliday
Author-email: graeme.holliday@pm.me
License: MIT
Platform: UNKNOWN
License-File: LICENSE
Requires-Dist: anyio (>=3.5.0)
Requires-Dist: asyncclick (>=8.0.3.2)
Requires-Dist: matplotlib (>=3.5.1)
Requires-Dist: pandas (>=1.4.0)
Requires-Dist: petl (>=1.7.7)
Requires-Dist: python-dateutil (>=2.8.2)
Requires-Dist: rich (>=11.1.0)
Requires-Dist: QuantLib (>=1.25)
Requires-Dist: tastyworks-api (>=4.2.2)
